jrImgTools-0.3.3.data/scripts/jrImgTools_setup
jrimgtools/__init__.py
jrimgtools/annotate.py
jrimgtools/demo.py
jrimgtools/imgIO.py
jrimgtools/metric.py
jrimgtools/utils.py
jrimgtools/process/__init__.py
jrimgtools/process/imgProcess.py
jrimgtools/visualization/__init__.py
jrimgtools/visualization/volSlicer.py
jrImgTools-0.3.3.dist-info/METADATA
jrImgTools-0.3.3.dist-info/WHEEL
jrImgTools-0.3.3.dist-info/top_level.txt
jrImgTools-0.3.3.dist-info/RECORD
