Metadata-Version: 2.1
Name: jrImgTools
Version: 0.3.3
Summary: Image utility functions for personal use
Home-page: https://github.com/jr-xing/jrImgTools
Author: Jerry Xing
Author-email: j.xing.www@gmail.com
License: UNKNOWN
Platform: UNKNOWN
Requires-Dist: numpy
Requires-Dist: scipy
Requires-Dist: pillow
Requires-Dist: matplotlib
Requires-Dist: SimpleITK
